kilovolt/__about__.py
kilovolt/__init__.py
kilovolt/_connection.py
kilovolt-0.2.0.dist-info/METADATA
kilovolt-0.2.0.dist-info/WHEEL
kilovolt-0.2.0.dist-info/licenses/LICENSE
kilovolt-0.2.0.dist-info/RECORD
